odoo/addons/report_xlsx_helper_demo/README.rst
odoo/addons/report_xlsx_helper_demo/__init__.py
odoo/addons/report_xlsx_helper_demo/__manifest__.py
odoo/addons/report_xlsx_helper_demo/i18n/report_xlsx_helper_demo.pot
odoo/addons/report_xlsx_helper_demo/models/__init__.py
odoo/addons/report_xlsx_helper_demo/models/res_partner.py
odoo/addons/report_xlsx_helper_demo/report/__init__.py
odoo/addons/report_xlsx_helper_demo/report/partner_export_xlsx.py
odoo/addons/report_xlsx_helper_demo/static/description/icon.png
odoo/addons/report_xlsx_helper_demo/views/res_partner.xml
odoo11_addon_report_xlsx_helper_demo-11.0.1.0.0.99.dev1.dist-info/METADATA
odoo11_addon_report_xlsx_helper_demo-11.0.1.0.0.99.dev1.dist-info/RECORD
odoo11_addon_report_xlsx_helper_demo-11.0.1.0.0.99.dev1.dist-info/WHEEL
odoo11_addon_report_xlsx_helper_demo-11.0.1.0.0.99.dev1.dist-info/top_level.txt
